AUTHORS
COPYING
ChangeLog
INSTALL
MANIFEST.in
setup.py
bin/pnuke
bin/prsync
bin/pscp
bin/pslurp
bin/pssh
pssh.egg-info/PKG-INFO
pssh.egg-info/SOURCES.txt
pssh.egg-info/dependency_links.txt
pssh.egg-info/top_level.txt
psshlib/__init__.py
psshlib/askpass.py
psshlib/cli.py
psshlib/color.py
psshlib/manager.py
psshlib/psshutil.py
psshlib/task.py
test/test.py