Metadata-Version: 1.0
Name: pssh
Version: 2.0
Summary: Parallel version of OpenSSH and related tools
Home-page: http://code.google.com/p/parallel-ssh/
Author: Andrew McNabb
Author-email: amcnabb@mcnabbs.org
License: BSD
Platform: linux
Classifier: Development Status :: 5 - Production/Stable
Classifier: Intended Audience :: System Administrators
Classifier: License :: OSI Approved :: BSD License
Classifier: Operating System :: POSIX
Classifier: Programming Language :: Python
Classifier: Topic :: Software Development :: Libraries :: Python Modules
Classifier: Topic :: System :: Clustering
Classifier: Topic :: System :: Networking
Classifier: Topic :: System :: Systems Administration
